pixsoup/__init__.py
pixsoup/cli.py
pixsoup/api/__init__.py
pixsoup/api/api.py
pixsoup/api/data.py
pixsoup/api/queries.py
pixsoup-0.1.3.dist-info/LICENSE.txt
pixsoup-0.1.3.dist-info/METADATA
pixsoup-0.1.3.dist-info/WHEEL
pixsoup-0.1.3.dist-info/entry_points.txt
pixsoup-0.1.3.dist-info/top_level.txt
pixsoup-0.1.3.dist-info/RECORD
