Metadata-Version: 2.1
Name: pixsoup
Version: 0.1.3
Summary: Easy StableDiffusion fine-tuning using PixSoup API.
Home-page: https://github.com/pixsoup/python
Keywords: pixsoup,stablediffusion,dreambooth
License-File: LICENSE.txt
Requires-Dist: aiohttp (>=3.8.3)
Requires-Dist: dotmap (>=1.3.30)
Requires-Dist: gql (>=3.4.0)
Requires-Dist: graphql-core (>=3.2.3)
Requires-Dist: click (>=8.0.4)
Requires-Dist: clint (>=0.5.1)
Requires-Dist: python-dateutil (>=2.8.2)
Requires-Dist: python-magic (>=0.4.27)
Requires-Dist: requests (>=2.27.1)
Requires-Dist: usersettings (>=1.1.5)
